README.rst
setup.py
baguette/__init__.py
baguette/baguette.ini
baguette/entrypoints.py
baguette/settings.py
baguette/utils.py
baguette/api/__init__.py
baguette/api/account.py
baguette/api/app.py
baguette/api/build.py
baguette/api/deployment.py
baguette/api/key.py
baguette/api/organization.py
baguette/api/vpc.py
baguette/commands/__init__.py
baguette/commands/account.py
baguette/commands/app.py
baguette/commands/build.py
baguette/commands/deployment.py
baguette/commands/key.py
baguette/commands/organization.py
baguette/commands/utils.py
baguette/commands/vpc.py
baguette/tests/__init__.py
baguette/tests/fixtures.py
baguette/tests/test_account.py
baguette/tests/test_app.py
baguette/tests/test_build.py
baguette/tests/test_deployment.py
baguette/tests/test_key.py
baguette/tests/test_organization.py
baguette/tests/test_settings.py
baguette/tests/test_utils.py
baguette/tests/test_vpc.py
baguette_client.egg-info/PKG-INFO
baguette_client.egg-info/SOURCES.txt
baguette_client.egg-info/dependency_links.txt
baguette_client.egg-info/entry_points.txt
baguette_client.egg-info/requires.txt
baguette_client.egg-info/top_level.txt