Metadata-Version: 1.1
Name: baguette-client
Version: 0.12
Summary: Baguette Command Line Interface
Home-page: https://github.com/baguette-io/baguette-client/
Author: UNKNOWN
Author-email: pydavid@baguette.io
License: UNKNOWN
Keywords: cli,baguette
Platform: UNKNOWN
Classifier: Programming Language :: Python
Classifier: Programming Language :: Python :: 2.7
Classifier: Programming Language :: Python :: 3.6
Classifier: License :: OSI Approved
Classifier: License :: OSI Approved :: GNU General Public License v3 (GPLv3)
Classifier: Operating System :: OS Independent
